tasklifo.py
tasklifo-0.1.0a1.dist-info/licenses/LICENSE
tasklifo-0.1.0a1.dist-info/METADATA
tasklifo-0.1.0a1.dist-info/WHEEL
tasklifo-0.1.0a1.dist-info/top_level.txt
tasklifo-0.1.0a1.dist-info/RECORD
