Metadata-Version: 2.4
Name: tasklifo
Version: 0.1.0a1
Summary: Last-in-first-out (LIFO), Git-inspired, LLM-assisted, Shell-friendly task manager for the busy and frequently interrupted.
Author-email: Jifeng Wu <jifengwu2k@gmail.com>
License-Expression: AGPL-3.0
Project-URL: Homepage, https://github.com/jifengwu2k/tasklifo
Project-URL: Bug Tracker, https://github.com/jifengwu2k/tasklifo/issues
Classifier: Programming Language :: Python :: 2
Classifier: Programming Language :: Python :: 3
Classifier: Operating System :: OS Independent
Requires-Python: >=2
License-File: LICENSE
Requires-Dist: chat-completions-conversation
Requires-Dist: get-multiline-input-with-editor
Requires-Dist: pytz
Requires-Dist: textcompat
Requires-Dist: typing; python_version < "3.5"
Dynamic: license-file
